{"fMJ7L9z4A2pTTRiV8TO0xQ==":"dsc07545-696x1044.jpg","60nmX/uoLC3uiyhmlcWm4A==":"dsc09035-696x1044.jpeg","GusqQeCbdBmg3osJVTEPoA==":"dsc09035-696x1044.jpg","p7qjroMTbHEuSsqz6dC1oA==":"dsc09294-696x1044.jpg","93djaYHLpxuVpS8BdhYH8A==":"dsc03590-952x1428.jpeg","YUykh8TDozEwFmaXBIvGCQ==":"dsc09471-2-1305x1305.jpg","heReIFVzGFBZ+3yrvRAnMg==":"dsc04310-2-2000x3000.jpg","u+UfCExVhEV6KJyghEjbEA==":"dsc00241-2-2000x2800.jpg","es2ZzPlH8kvW7aTyb9PmrA==":"dsc08546-2000x3000.jpg","Z6snbdPsUZSx6ix67qwDtA==":"dsc09856-2000x2800.jpg","uyk0UrQjD8lvgxGtAq5cCg==":"dsc01882-2000x3000.jpg","Y4r2lBYpxVsB12IuXYs7bA==":"dsc08557-2000x3000.jpg","5OOkc/63EpoHEzposnkKfQ==":"dsc08807-2000x3000.jpg","+G/EKzulWCR3AlOl0jkYTg==":"dsc00987-2000x3000.jpg","rTov5X2x4MR1E4PMswoXuQ==":"qlfawvnw-2000x2800.jpg","mboi7qODq+o2QcrTHJ+L8g==":"dsc06494-2000x3000.jpg","262KrIIDmOyjKxuFcQ/8nA==":"dsc09294-696x1044.jpeg","Jk3N9H8HuG1CAzq508MzAg==":"dsc09388-696x1044.jpg"}